test/__init__.py
test/term_info_queries_test.py
vfb_queries-0.1.4a0.dist-info/LICENSE
vfb_queries-0.1.4a0.dist-info/METADATA
vfb_queries-0.1.4a0.dist-info/WHEEL
vfb_queries-0.1.4a0.dist-info/top_level.txt
vfb_queries-0.1.4a0.dist-info/RECORD
