Metadata-Version: 2.1
Name: vfb-queries
Version: 0.1.4a0
Summary: Wrapper for querying VirtualFlyBrain knowledge graph.
Home-page: https://github.com/VirtualFlyBrain/VFB_queries
Author: VirtualFlyBrain
License: GPL-3.0 License
Project-URL: Bug Reports, https://github.com/VirtualFlyBrain/VFB_queries/issues
Project-URL: Source, https://github.com/VirtualFlyBrain/VFB_queries
Classifier: Programming Language :: Python :: 3
Classifier: License :: OSI Approved :: GNU General Public License v3 (GPLv3)
Classifier: Operating System :: OS Independent
License-File: LICENSE
Requires-Dist: vfb-connect
Requires-Dist: dataclasses-json
Requires-Dist: dacite
Requires-Dist: requests
Requires-Dist: pysolr
